{"nodes": [{"id": 0, "size": 134, "stability:": 0.7880764089997772}, {"id": 1, "size": 60, "stability:": 0.8260999999999998}, {"id": 2, "size": 9, "stability:": 1.0}, {"id": 3, "size": 19, "stability:": 0.8472022160664818}, {"id": 4, "size": 9, "stability:": 0.5886419753086418}, {"id": 5, "size": 88, "stability:": 0.6923657024793388}, {"id": 6, "size": 11, "stability:": 1.0}, {"id": 7, "size": 29, "stability:": 0.5436623067776456}, {"id": 8, "size": 29, "stability:": 1.0000000000000002}, {"id": 9, "size": 65, "stability:": 0.9979171597633139}], "edges": [{"source": 0, "target": 1, "instability": 0.0009402985074626865}, {"source": 0, "target": 2, "instability": 0.0}, {"source": 0, "target": 3, "instability": 0.0}, {"source": 0, "target": 4, "instability": 1.658374792703151e-05}, {"source": 0, "target": 5, "instability": 0.06836414518317503}, {"source": 0, "target": 6, "instability": 0.0}, {"source": 0, "target": 7, "instability": 0.312699433865157}, {"source": 0, "target": 8, "instability": 0.0}, {"source": 0, "target": 9, "instability": 0.0}, {"source": 1, "target": 2, "instability": 0.0005}, {"source": 1, "target": 3, "instability": 0.0}, {"source": 1, "target": 4, "instability": 0.02718518518518519}, {"source": 1, "target": 5, "instability": 0.041558712121212114}, {"source": 1, "target": 6, "instability": 0.0}, {"source": 1, "target": 7, "instability": 0.00022988505747126436}, {"source": 1, "target": 8, "instability": 0.0}, {"source": 1, "target": 9, "instability": 0.07226666666666666}, {"source": 2, "target": 3, "instability": 0.0}, {"source": 2, "target": 4, "instability": 0.10555555555555556}, {"source": 2, "target": 5, "instability": 0.0}, {"source": 2, "target": 6, "instability": 0.0}, {"source": 2, "target": 7, "instability": 0.0}, {"source": 2, "target": 8, "instability": 0.0}, {"source": 2, "target": 9, "instability": 0.0}, {"source": 3, "target": 4, "instability": 0.009298245614035087}, {"source": 3, "target": 5, "instability": 0.0}, {"source": 3, "target": 6, "instability": 0.005263157894736842}, {"source": 3, "target": 7, "instability": 0.3163520871143376}, {"source": 3, "target": 8, "instability": 0.0}, {"source": 3, "target": 9, "instability": 0.0}, {"source": 4, "target": 5, "instability": 0.09357323232323232}, {"source": 4, "target": 6, "instability": 0.0}, {"source": 4, "target": 7, "instability": 0.00019157088122605362}, {"source": 4, "target": 8, "instability": 0.0}, {"source": 4, "target": 9, "instability": 0.0}, {"source": 5, "target": 6, "instability": 0.0}, {"source": 5, "target": 7, "instability": 0.011802507836990595}, {"source": 5, "target": 8, "instability": 0.004431818181818181}, {"source": 5, "target": 9, "instability": 3.4965034965034966e-06}, {"source": 6, "target": 7, "instability": 0.0}, {"source": 6, "target": 8, "instability": 0.0}, {"source": 6, "target": 9, "instability": 0.0}, {"source": 7, "target": 8, "instability": 0.0}, {"source": 7, "target": 9, "instability": 0.0}, {"source": 8, "target": 9, "instability": 0.0}]}