{"nodes": [{"id": 0, "size": 39, "stability:": 29.43692307692308}, {"id": 1, "size": 71, "stability:": 44.98929577464787}, {"id": 2, "size": 65, "stability:": 52.78215384615386}, {"id": 3, "size": 32, "stability:": 27.516875}, {"id": 4, "size": 23, "stability:": 11.96086956521739}, {"id": 5, "size": 6, "stability:": 4.916666666666668}, {"id": 6, "size": 32, "stability:": 15.021874999999998}, {"id": 7, "size": 11, "stability:": 10.0}, {"id": 8, "size": 28, "stability:": 17.667142857142853}, {"id": 9, "size": 16, "stability:": 7.5375}, {"id": 10, "size": 5, "stability:": 3.9999999999999996}, {"id": 11, "size": 50, "stability:": 43.68120000000001}, {"id": 12, "size": 54, "stability:": 36.34148148148149}, {"id": 13, "size": 9, "stability:": 6.34}, {"id": 14, "size": 4, "stability:": 3.0}, {"id": 15, "size": 8, "stability:": 6.999999999999997}], "edges": [{"source": 0, "target": 1, "instability": 0.009691894950712406}, {"source": 0, "target": 2, "instability": 1.5867314847615928}, {"source": 0, "target": 3, "instability": 0.0}, {"source": 0, "target": 4, "instability": 0.010684489012706846}, {"source": 0, "target": 5, "instability": 0.0026148818018424543}, {"source": 0, "target": 6, "instability": 1.2953249270614178}, {"source": 0, "target": 7, "instability": 0.0}, {"source": 0, "target": 8, "instability": 1.5042930324483084}, {"source": 0, "target": 9, "instability": 0.05684549460080592}, {"source": 0, "target": 10, "instability": 0.0}, {"source": 0, "target": 11, "instability": 1.1974961913113242}, {"source": 0, "target": 12, "instability": 0.0}, {"source": 0, "target": 13, "instability": 0.03202563076101743}, {"source": 0, "target": 14, "instability": 0.0}, {"source": 0, "target": 15, "instability": 0.0}, {"source": 1, "target": 2, "instability": 0.017075449166772175}, {"source": 1, "target": 3, "instability": 0.00839181358296689}, {"source": 1, "target": 4, "instability": 2.4550613952360636}, {"source": 1, "target": 5, "instability": 0.0029070094986690556}, {"source": 1, "target": 6, "instability": 4.622420716837738}, {"source": 1, "target": 7, "instability": 0.0}, {"source": 1, "target": 8, "instability": 0.7443874840149779}, {"source": 1, "target": 9, "instability": 0.0008900862436453899}, {"source": 1, "target": 10, "instability": 0.0}, {"source": 1, "target": 11, "instability": 0.004195906791483445}, {"source": 1, "target": 12, "instability": 16.477252839511614}, {"source": 1, "target": 13, "instability": 0.2527844931952908}, {"source": 1, "target": 14, "instability": 0.0}, {"source": 1, "target": 15, "instability": 0.0}, {"source": 2, "target": 3, "instability": 0.0}, {"source": 2, "target": 4, "instability": 0.0}, {"source": 2, "target": 5, "instability": 0.0}, {"source": 2, "target": 6, "instability": 0.10963225241337868}, {"source": 2, "target": 7, "instability": 0.0}, {"source": 2, "target": 8, "instability": 0.38371871852315853}, {"source": 2, "target": 9, "instability": 0.004961389383568339}, {"source": 2, "target": 10, "instability": 0.0}, {"source": 2, "target": 11, "instability": 0.0017541160386140586}, {"source": 2, "target": 12, "instability": 0.0033757978902788886}, {"source": 2, "target": 13, "instability": 0.0008268982305947231}, {"source": 2, "target": 14, "instability": 0.0}, {"source": 2, "target": 15, "instability": 0.0}, {"source": 3, "target": 4, "instability": 0.0007372097807744856}, {"source": 3, "target": 5, "instability": 0.0}, {"source": 3, "target": 6, "instability": 0.1553125}, {"source": 3, "target": 7, "instability": 0.0}, {"source": 3, "target": 8, "instability": 0.0}, {"source": 3, "target": 9, "instability": 0.03226174689163623}, {"source": 3, "target": 10, "instability": 0.0}, {"source": 3, "target": 11, "instability": 0.0004999999999999999}, {"source": 3, "target": 12, "instability": 0.5042192350922732}, {"source": 3, "target": 13, "instability": 0.12020815280171306}, {"source": 3, "target": 14, "instability": 0.0}, {"source": 3, "target": 15, "instability": 0.0}, {"source": 4, "target": 5, "instability": 0.010215078369104985}, {"source": 4, "target": 6, "instability": 4.73251818768181}, {"source": 4, "target": 7, "instability": 0.0}, {"source": 4, "target": 8, "instability": 0.3976016999476263}, {"source": 4, "target": 9, "instability": 0.8184190751740184}, {"source": 4, "target": 10, "instability": 5.893430388078782}, {"source": 4, "target": 11, "instability": 0.007077213895435063}, {"source": 4, "target": 12, "instability": 0.09136820096810568}, {"source": 4, "target": 13, "instability": 0.0006950480468569159}, {"source": 4, "target": 14, "instability": 4.145266551454647}, {"source": 4, "target": 15, "instability": 0.0}, {"source": 5, "target": 6, "instability": 0.06350852961085884}, {"source": 5, "target": 7, "instability": 0.0}, {"source": 5, "target": 8, "instability": 0.02391701924412425}, {"source": 5, "target": 9, "instability": 1.0308269334212543}, {"source": 5, "target": 10, "instability": 0.0}, {"source": 5, "target": 11, "instability": 0.0017320508075688774}, {"source": 5, "target": 12, "instability": 0.0}, {"source": 5, "target": 13, "instability": 0.0013608276348795435}, {"source": 5, "target": 14, "instability": 0.17962924780409975}, {"source": 5, "target": 15, "instability": 0.0}, {"source": 6, "target": 7, "instability": 0.0}, {"source": 6, "target": 8, "instability": 2.49388146359531}, {"source": 6, "target": 9, "instability": 0.10385630848677416}, {"source": 6, "target": 10, "instability": 0.0}, {"source": 6, "target": 11, "instability": 2.3099999999999996}, {"source": 6, "target": 12, "instability": 0.8922467285101341}, {"source": 6, "target": 13, "instability": 0.12256517540566823}, {"source": 6, "target": 14, "instability": 0.0}, {"source": 6, "target": 15, "instability": 0.0}, {"source": 7, "target": 8, "instability": 0.0}, {"source": 7, "target": 9, "instability": 0.049749371855331}, {"source": 7, "target": 10, "instability": 0.0}, {"source": 7, "target": 11, "instability": 0.0}, {"source": 7, "target": 12, "instability": 0.0}, {"source": 7, "target": 13, "instability": 0.0}, {"source": 7, "target": 14, "instability": 0.0}, {"source": 7, "target": 15, "instability": 0.0}, {"source": 8, "target": 9, "instability": 0.19937625951236737}, {"source": 8, "target": 10, "instability": 0.0}, {"source": 8, "target": 11, "instability": 0.060401040672207904}, {"source": 8, "target": 12, "instability": 0.006429306248420496}, {"source": 8, "target": 13, "instability": 0.6387599593855939}, {"source": 8, "target": 14, "instability": 0.0}, {"source": 8, "target": 15, "instability": 0.0}, {"source": 9, "target": 10, "instability": 0.6428695435311894}, {"source": 9, "target": 11, "instability": 0.016263455967290594}, {"source": 9, "target": 12, "instability": 0.09457752062412826}, {"source": 9, "target": 13, "instability": 0.4683333333333334}, {"source": 9, "target": 14, "instability": 0.775}, {"source": 9, "target": 15, "instability": 0.04949747468305833}, {"source": 10, "target": 11, "instability": 0.0}, {"source": 10, "target": 12, "instability": 0.0}, {"source": 10, "target": 13, "instability": 0.0}, {"source": 10, "target": 14, "instability": 2.4596747752497685}, {"source": 10, "target": 15, "instability": 0.0}, {"source": 11, "target": 12, "instability": 0.0013471506281091269}, {"source": 11, "target": 13, "instability": 0.004714045207910317}, {"source": 11, "target": 14, "instability": 0.0}, {"source": 11, "target": 15, "instability": 0.0}, {"source": 12, "target": 13, "instability": 1.0237959906410434}, {"source": 12, "target": 14, "instability": 0.0}, {"source": 12, "target": 15, "instability": 0.026943012562182532}, {"source": 13, "target": 14, "instability": 0.0}, {"source": 13, "target": 15, "instability": 0.0}, {"source": 14, "target": 15, "instability": 0.0}]}