{"nodes": [{"id": 0, "weight": 1.0}, {"id": 1, "weight": 1.0}, {"id": 2, "weight": 1.0}, {"id": 3, "weight": 1.0}, {"id": 4, "weight": 1.0}, {"id": 5, "weight": 1.0}, {"id": 6, "weight": 1.0}, {"id": 7, "weight": 1.0}, {"id": 8, "weight": 1.0}, {"id": 9, "weight": 1.0}, {"id": 10, "weight": 1.0}, {"id": 11, "weight": 1.0}, {"id": 12, "weight": 1.0}, {"id": 13, "weight": 1.0}, {"id": 14, "weight": 1.0}, {"id": 15, "weight": 1.0}, {"id": 16, "weight": 1.0}, {"id": 17, "weight": 1.0}, {"id": 18, "weight": 1.0}, {"id": 19, "weight": 1.0}, {"id": 20, "weight": 1.0}, {"id": 21, "weight": 1.0}, {"id": 22, "weight": 1.0}, {"id": 23, "weight": 1.0}, {"id": 24, "weight": 1.0}, {"id": 25, "weight": 1.0}, {"id": 26, "weight": 1.0}, {"id": 27, "weight": 1.0}, {"id": 28, "weight": 1.0}, {"id": 29, "weight": 1.0}, {"id": 30, "weight": 1.0}, {"id": 31, "weight": 1.0}, {"id": 32, "weight": 1.0}, {"id": 33, "weight": 1.0}, {"id": 34, "weight": 1.0}, {"id": 35, "weight": 1.0}, {"id": 36, "weight": 1.0}, {"id": 37, "weight": 1.0}, {"id": 38, "weight": 1.0}, {"id": 39, "weight": 1.0}, {"id": 40, "weight": 1.0}, {"id": 41, "weight": 1.0}, {"id": 42, "weight": 1.0}, {"id": 43, "weight": 1.0}, {"id": 44, "weight": 1.0}, {"id": 45, "weight": 1.0}, {"id": 46, "weight": 1.0}, {"id": 47, "weight": 1.0}, {"id": 48, "weight": 1.0}, {"id": 49, "weight": 1.0}, {"id": 50, "weight": 1.0}, {"id": 51, "weight": 1.0}, {"id": 52, "weight": 1.0}, {"id": 53, "weight": 1.0}, {"id": 54, "weight": 1.0}, {"id": 55, "weight": 1.0}, {"id": 56, "weight": 1.0}, {"id": 57, "weight": 1.0}, {"id": 58, "weight": 1.0}, {"id": 59, "weight": 1.0}, {"id": 60, "weight": 1.0}, {"id": 61, "weight": 1.0}, {"id": 62, "weight": 1.0}, {"id": 63, "weight": 1.0}, {"id": 64, "weight": 1.0}, {"id": 65, "weight": 1.0}, {"id": 66, "weight": 1.0}, {"id": 67, "weight": 1.0}, {"id": 68, "weight": 1.0}, {"id": 69, "weight": 1.0}, {"id": 70, "weight": 1.0}, {"id": 71, "weight": 1.0}, {"id": 72, "weight": 1.0}, {"id": 73, "weight": 1.0}, {"id": 74, "weight": 1.0}, {"id": 75, "weight": 1.0}, {"id": 76, "weight": 1.0}, {"id": 77, "weight": 1.0}, {"id": 78, "weight": 1.0}, {"id": 79, "weight": 1.0}, {"id": 80, "weight": 1.0}, {"id": 81, "weight": 1.0}, {"id": 82, "weight": 1.0}, {"id": 83, "weight": 1.0}, {"id": 84, "weight": 1.0}, {"id": 85, "weight": 1.0}, {"id": 86, "weight": 1.0}, {"id": 87, "weight": 1.0}, {"id": 88, "weight": 1.0}, {"id": 89, "weight": 1.0}, {"id": 90, "weight": 1.0}, {"id": 91, "weight": 1.0}, {"id": 92, "weight": 1.0}, {"id": 93, "weight": 1.0}, {"id": 94, "weight": 1.0}, {"id": 95, "weight": 1.0}, {"id": 96, "weight": 1.0}, {"id": 97, "weight": 1.0}, {"id": 98, "weight": 1.0}, {"id": 99, "weight": 1.0}], "links": [{"source": 0, "target": 1, "weight": 2.0}, {"source": 0, "target": 2, "weight": 2.0}, {"source": 0, "target": 3, "weight": 2.0}, {"source": 0, "target": 4, "weight": 2.0}, {"source": 0, "target": 5, "weight": 2.7480619844738428}, {"source": 0, "target": 7, "weight": 2.7438665660068686}, {"source": 0, "target": 8, "weight": 2.0}, {"source": 0, "target": 9, "weight": 2.0}, {"source": 0, "target": 13, "weight": 2.0}, {"source": 0, "target": 14, "weight": 2.0}, {"source": 0, "target": 15, "weight": 2.0}, {"source": 0, "target": 16, "weight": 2.0}, {"source": 0, "target": 17, "weight": 2.0}, {"source": 0, "target": 18, "weight": 2.0}, {"source": 0, "target": 19, "weight": 2.0}, {"source": 0, "target": 20, "weight": 2.0}, {"source": 0, "target": 21, "weight": 2.7437187949134767}, {"source": 0, "target": 22, "weight": 2.745628885013484}, {"source": 0, "target": 23, "weight": 2.0}, {"source": 0, "target": 24, "weight": 2.0}, {"source": 1, "target": 2, "weight": 2.0}, {"source": 1, "target": 3, "weight": 2.0}, {"source": 1, "target": 4, "weight": 2.0}, {"source": 1, "target": 5, "weight": 2.0}, {"source": 1, "target": 6, "weight": 2.0}, {"source": 1, "target": 7, "weight": 2.0}, {"source": 1, "target": 8, "weight": 2.0}, {"source": 1, "target": 9, "weight": 2.7411539527083177}, {"source": 1, "target": 10, "weight": 2.0}, {"source": 1, "target": 11, "weight": 2.0}, {"source": 1, "target": 12, "weight": 2.0}, {"source": 1, "target": 13, "weight": 2.0}, {"source": 1, "target": 14, "weight": 2.7415014622396114}, {"source": 1, "target": 15, "weight": 2.0}, {"source": 1, "target": 16, "weight": 2.0}, {"source": 1, "target": 17, "weight": 2.0}, {"source": 1, "target": 18, "weight": 2.0}, {"source": 1, "target": 19, "weight": 2.0}, {"source": 1, "target": 20, "weight": 2.0}, {"source": 1, "target": 21, "weight": 2.0}, {"source": 1, "target": 22, "weight": 3.8087285811804854}, {"source": 1, "target": 23, "weight": 2.0}, {"source": 1, "target": 24, "weight": 2.0}, {"source": 2, "target": 3, "weight": 2.0}, {"source": 2, "target": 4, "weight": 2.7453031716570195}, {"source": 2, "target": 5, "weight": 2.0}, {"source": 2, "target": 6, "weight": 2.0}, {"source": 2, "target": 7, "weight": 2.0}, {"source": 2, "target": 8, "weight": 2.0}, {"source": 2, "target": 9, "weight": 2.0}, {"source": 2, "target": 10, "weight": 2.0}, {"source": 2, "target": 12, "weight": 2.0}, {"source": 2, "target": 13, "weight": 2.0}, {"source": 2, "target": 14, "weight": 2.0}, {"source": 2, "target": 15, "weight": 2.0}, {"source": 2, "target": 16, "weight": 2.0}, {"source": 2, "target": 17, "weight": 2.0}, {"source": 2, "target": 18, "weight": 3.845699387103629}, {"source": 2, "target": 19, "weight": 2.0}, {"source": 2, "target": 20, "weight": 2.0}, {"source": 2, "target": 21, "weight": 2.0}, {"source": 2, "target": 22, "weight": 2.7428712689825776}, {"source": 2, "target": 23, "weight": 2.0}, {"source": 2, "target": 24, "weight": 2.0}, {"source": 3, "target": 4, "weight": 2.0}, {"source": 3, "target": 5, "weight": 2.0}, {"source": 3, "target": 6, "weight": 2.0}, {"source": 3, "target": 7, "weight": 2.0}, {"source": 3, "target": 8, "weight": 2.0}, {"source": 3, "target": 9, "weight": 2.0}, {"source": 3, "target": 10, "weight": 2.738433919981791}, {"source": 3, "target": 11, "weight": 2.0}, {"source": 3, "target": 12, "weight": 2.0}, {"source": 3, "target": 13, "weight": 2.0}, {"source": 3, "target": 14, "weight": 2.0}, {"source": 3, "target": 15, "weight": 2.0}, {"source": 3, "target": 16, "weight": 2.0}, {"source": 3, "target": 17, "weight": 2.0}, {"source": 3, "target": 18, "weight": 2.0}, {"source": 3, "target": 19, "weight": 2.737694224211787}, {"source": 3, "target": 20, "weight": 2.0}, {"source": 3, "target": 21, "weight": 2.0}, {"source": 3, "target": 22, "weight": 2.7355006548403686}, {"source": 3, "target": 23, "weight": 2.0}, {"source": 3, "target": 24, "weight": 2.738633167150081}, {"source": 4, "target": 5, "weight": 2.0}, {"source": 4, "target": 6, "weight": 2.7486289492298073}, {"source": 4, "target": 7, "weight": 2.0}, {"source": 4, "target": 8, "weight": 2.0}, {"source": 4, "target": 9, "weight": 2.0}, {"source": 4, "target": 10, "weight": 2.0}, {"source": 4, "target": 11, "weight": 2.0}, {"source": 4, "target": 12, "weight": 2.0}, {"source": 4, "target": 13, "weight": 2.744330892491288}, {"source": 4, "target": 14, "weight": 2.0}, {"source": 4, "target": 15, "weight": 2.0}, {"source": 4, "target": 16, "weight": 2.7470282626595184}, {"source": 4, "target": 17, "weight": 2.0}, {"source": 4, "target": 19, "weight": 2.0}, {"source": 4, "target": 20, "weight": 2.0}, {"source": 4, "target": 21, "weight": 2.7407887490148988}, {"source": 4, "target": 22, "weight": 2.0}, {"source": 4, "target": 23, "weight": 2.0}, {"source": 4, "target": 24, "weight": 2.0}, {"source": 5, "target": 6, "weight": 2.0}, {"source": 5, "target": 7, "weight": 2.0}, {"source": 5, "target": 8, "weight": 2.7464090692771537}, {"source": 5, "target": 9, "weight": 2.0}, {"source": 5, "target": 10, "weight": 2.0}, {"source": 5, "target": 11, "weight": 2.0}, {"source": 5, "target": 12, "weight": 2.7484311482029886}, {"source": 5, "target": 13, "weight": 2.0}, {"source": 5, "target": 14, "weight": 2.743783081673227}, {"source": 5, "target": 18, "weight": 2.0}, {"source": 5, "target": 19, "weight": 2.0}, {"source": 5, "target": 20, "weight": 2.0}, {"source": 5, "target": 21, "weight": 2.0}, {"source": 5, "target": 22, "weight": 2.0}, {"source": 5, "target": 23, "weight": 2.0}, {"source": 5, "target": 24, "weight": 2.0}, {"source": 6, "target": 7, "weight": 2.0}, {"source": 6, "target": 8, "weight": 2.0}, {"source": 6, "target": 9, "weight": 2.0}, {"source": 6, "target": 10, "weight": 2.746857187622826}, {"source": 6, "target": 11, "weight": 2.746268656716418}, {"source": 6, "target": 12, "weight": 2.7531212096808115}, {"source": 6, "target": 13, "weight": 2.0}, {"source": 6, "target": 15, "weight": 2.0}, {"source": 6, "target": 17, "weight": 2.0}, {"source": 6, "target": 18, "weight": 2.0}, {"source": 6, "target": 19, "weight": 2.0}, {"source": 6, "target": 20, "weight": 2.0}, {"source": 6, "target": 21, "weight": 2.743331042697004}, {"source": 6, "target": 22, "weight": 2.0}, {"source": 6, "target": 23, "weight": 2.7521356272080832}, {"source": 6, "target": 24, "weight": 2.0}, {"source": 7, "target": 9, "weight": 2.7381264673678443}, {"source": 7, "target": 10, "weight": 2.0}, {"source": 7, "target": 11, "weight": 2.0}, {"source": 7, "target": 12, "weight": 2.738449196494141}, {"source": 7, "target": 13, "weight": 2.7321038319459325}, {"source": 7, "target": 14, "weight": 2.733463015561349}, {"source": 7, "target": 15, "weight": 2.0}, {"source": 7, "target": 16, "weight": 2.0}, {"source": 7, "target": 17, "weight": 2.0}, {"source": 7, "target": 18, "weight": 2.0}, {"source": 7, "target": 19, "weight": 2.0}, {"source": 7, "target": 20, "weight": 2.0}, {"source": 7, "target": 21, "weight": 2.7313990990746055}, {"source": 7, "target": 22, "weight": 2.0}, {"source": 7, "target": 23, "weight": 2.0}, {"source": 7, "target": 24, "weight": 2.0}, {"source": 8, "target": 9, "weight": 2.0}, {"source": 8, "target": 11, "weight": 2.748899566313353}, {"source": 8, "target": 12, "weight": 2.0}, {"source": 8, "target": 15, "weight": 2.0}, {"source": 8, "target": 16, "weight": 2.0}, {"source": 8, "target": 17, "weight": 2.0}, {"source": 8, "target": 18, "weight": 2.0}, {"source": 8, "target": 19, "weight": 2.0}, {"source": 8, "target": 20, "weight": 2.0}, {"source": 8, "target": 21, "weight": 2.0}, {"source": 8, "target": 22, "weight": 2.745377378329879}, {"source": 8, "target": 23, "weight": 2.7549037001962176}, {"source": 8, "target": 24, "weight": 2.0}, {"source": 9, "target": 10, "weight": 2.0}, {"source": 9, "target": 11, "weight": 2.746914178768109}, {"source": 9, "target": 12, "weight": 2.0}, {"source": 9, "target": 13, "weight": 2.0}, {"source": 9, "target": 14, "weight": 2.0}, {"source": 9, "target": 15, "weight": 2.0}, {"source": 9, "target": 16, "weight": 2.0}, {"source": 9, "target": 17, "weight": 2.0}, {"source": 9, "target": 18, "weight": 2.0}, {"source": 9, "target": 19, "weight": 2.7456236310671165}, {"source": 9, "target": 20, "weight": 2.7475223766500623}, {"source": 9, "target": 21, "weight": 2.736476747995094}, {"source": 9, "target": 22, "weight": 2.0}, {"source": 9, "target": 23, "weight": 2.0}, {"source": 9, "target": 24, "weight": 2.744283663449692}, {"source": 10, "target": 11, "weight": 2.0}, {"source": 10, "target": 12, "weight": 2.7467415297560236}, {"source": 10, "target": 13, "weight": 2.740989125948919}, {"source": 10, "target": 14, "weight": 2.743192188949723}, {"source": 10, "target": 15, "weight": 2.0}, {"source": 10, "target": 16, "weight": 2.7437608951976102}, {"source": 10, "target": 17, "weight": 2.744808726431274}, {"source": 10, "target": 18, "weight": 2.0}, {"source": 10, "target": 19, "weight": 2.0}, {"source": 10, "target": 20, "weight": 2.0}, {"source": 10, "target": 21, "weight": 2.0}, {"source": 10, "target": 22, "weight": 2.0}, {"source": 10, "target": 23, "weight": 2.0}, {"source": 10, "target": 24, "weight": 2.0}, {"source": 11, "target": 12, "weight": 2.0}, {"source": 11, "target": 13, "weight": 2.0}, {"source": 11, "target": 14, "weight": 2.747037544124635}, {"source": 11, "target": 15, "weight": 2.7514195339549645}, {"source": 11, "target": 16, "weight": 2.0}, {"source": 11, "target": 17, "weight": 2.7501894880220155}, {"source": 11, "target": 18, "weight": 2.0}, {"source": 11, "target": 19, "weight": 2.0}, {"source": 11, "target": 20, "weight": 2.0}, {"source": 11, "target": 23, "weight": 2.0}, {"source": 11, "target": 24, "weight": 2.0}, {"source": 12, "target": 13, "weight": 2.0}, {"source": 12, "target": 14, "weight": 2.0}, {"source": 12, "target": 15, "weight": 2.0}, {"source": 12, "target": 16, "weight": 2.0}, {"source": 12, "target": 17, "weight": 2.0}, {"source": 12, "target": 18, "weight": 2.0}, {"source": 12, "target": 19, "weight": 2.0}, {"source": 12, "target": 20, "weight": 2.0}, {"source": 12, "target": 21, "weight": 3.8015933605138006}, {"source": 12, "target": 22, "weight": 2.0}, {"source": 12, "target": 23, "weight": 2.0}, {"source": 13, "target": 14, "weight": 2.0}, {"source": 13, "target": 15, "weight": 2.0}, {"source": 13, "target": 16, "weight": 2.0}, {"source": 13, "target": 17, "weight": 2.0}, {"source": 13, "target": 18, "weight": 2.0}, {"source": 13, "target": 19, "weight": 2.0}, {"source": 13, "target": 21, "weight": 2.0}, {"source": 13, "target": 22, "weight": 2.7411627419544167}, {"source": 13, "target": 24, "weight": 2.0}, {"source": 14, "target": 16, "weight": 2.0}, {"source": 14, "target": 17, "weight": 2.0}, {"source": 14, "target": 19, "weight": 2.742202188757931}, {"source": 14, "target": 20, "weight": 2.7454482955749}, {"source": 14, "target": 21, "weight": 2.0}, {"source": 14, "target": 22, "weight": 2.0}, {"source": 14, "target": 23, "weight": 2.0}, {"source": 14, "target": 24, "weight": 2.0}, {"source": 15, "target": 16, "weight": 2.0}, {"source": 15, "target": 17, "weight": 2.0}, {"source": 15, "target": 18, "weight": 2.7503323390116505}, {"source": 15, "target": 19, "weight": 2.748102452474939}, {"source": 15, "target": 21, "weight": 2.742506504592899}, {"source": 15, "target": 22, "weight": 2.7428307818663535}, {"source": 15, "target": 23, "weight": 2.749358452372543}, {"source": 15, "target": 24, "weight": 2.745898012959865}, {"source": 16, "target": 17, "weight": 2.0}, {"source": 16, "target": 18, "weight": 2.0}, {"source": 16, "target": 19, "weight": 2.746268656716418}, {"source": 16, "target": 20, "weight": 2.0}, {"source": 16, "target": 21, "weight": 2.0}, {"source": 16, "target": 22, "weight": 3.80704789357455}, {"source": 16, "target": 23, "weight": 2.0}, {"source": 16, "target": 24, "weight": 2.744359038903571}, {"source": 17, "target": 18, "weight": 2.0}, {"source": 17, "target": 19, "weight": 2.0}, {"source": 17, "target": 20, "weight": 2.0}, {"source": 17, "target": 21, "weight": 2.0}, {"source": 17, "target": 22, "weight": 2.0}, {"source": 17, "target": 23, "weight": 2.0}, {"source": 17, "target": 24, "weight": 2.0}, {"source": 18, "target": 19, "weight": 2.0}, {"source": 18, "target": 22, "weight": 2.0}, {"source": 18, "target": 23, "weight": 2.0}, {"source": 18, "target": 24, "weight": 2.754009930605519}, {"source": 19, "target": 20, "weight": 2.7476558473174224}, {"source": 19, "target": 21, "weight": 2.0}, {"source": 19, "target": 22, "weight": 2.0}, {"source": 19, "target": 24, "weight": 2.0}, {"source": 20, "target": 21, "weight": 2.0}, {"source": 20, "target": 22, "weight": 2.0}, {"source": 20, "target": 23, "weight": 2.0}, {"source": 20, "target": 24, "weight": 2.0}, {"source": 21, "target": 22, "weight": 2.0}, {"source": 21, "target": 23, "weight": 2.0}, {"source": 21, "target": 24, "weight": 2.7403772296662967}, {"source": 22, "target": 23, "weight": 2.0}, {"source": 22, "target": 24, "weight": 2.0}, {"source": 23, "target": 24, "weight": 2.0}, {"source": 25, "target": 26, "weight": 2.0}, {"source": 25, "target": 28, "weight": 2.0}, {"source": 25, "target": 29, "weight": 2.0}, {"source": 25, "target": 30, "weight": 2.753272152272795}, {"source": 25, "target": 31, "weight": 2.0}, {"source": 25, "target": 32, "weight": 2.0}, {"source": 25, "target": 34, "weight": 2.0}, {"source": 25, "target": 35, "weight": 2.0}, {"source": 25, "target": 36, "weight": 2.0}, {"source": 25, "target": 37, "weight": 2.7503376133198523}, {"source": 25, "target": 38, "weight": 2.7454560830621038}, {"source": 25, "target": 39, "weight": 2.0}, {"source": 25, "target": 41, "weight": 2.0}, {"source": 25, "target": 42, "weight": 2.741681087816225}, {"source": 25, "target": 43, "weight": 2.750348231216169}, {"source": 25, "target": 44, "weight": 2.752885583697464}, {"source": 25, "target": 46, "weight": 2.0}, {"source": 25, "target": 47, "weight": 2.0}, {"source": 25, "target": 48, "weight": 2.0}, {"source": 25, "target": 49, "weight": 2.0}, {"source": 26, "target": 27, "weight": 2.0}, {"source": 26, "target": 28, "weight": 2.0}, {"source": 26, "target": 29, "weight": 2.0}, {"source": 26, "target": 31, "weight": 2.74708875700606}, {"source": 26, "target": 34, "weight": 2.0}, {"source": 26, "target": 35, "weight": 2.0}, {"source": 26, "target": 36, "weight": 2.0}, {"source": 26, "target": 37, "weight": 2.0}, {"source": 26, "target": 38, "weight": 2.0}, {"source": 26, "target": 39, "weight": 2.0}, {"source": 26, "target": 40, "weight": 2.0}, {"source": 26, "target": 41, "weight": 2.0}, {"source": 26, "target": 42, "weight": 2.0}, {"source": 26, "target": 43, "weight": 2.0}, {"source": 26, "target": 44, "weight": 2.749964648367736}, {"source": 26, "target": 45, "weight": 2.0}, {"source": 26, "target": 46, "weight": 3.822351849394247}, {"source": 26, "target": 47, "weight": 2.0}, {"source": 26, "target": 48, "weight": 2.7476177921735525}, {"source": 26, "target": 49, "weight": 2.0}, {"source": 27, "target": 28, "weight": 2.0}, {"source": 27, "target": 29, "weight": 2.0}, {"source": 27, "target": 31, "weight": 2.0}, {"source": 27, "target": 32, "weight": 2.7501779359430607}, {"source": 27, "target": 33, "weight": 2.0}, {"source": 27, "target": 34, "weight": 2.0}, {"source": 27, "target": 35, "weight": 2.0}, {"source": 27, "target": 37, "weight": 2.0}, {"source": 27, "target": 38, "weight": 2.0}, {"source": 27, "target": 39, "weight": 2.749372382276405}, {"source": 27, "target": 40, "weight": 2.7492007086298074}, {"source": 27, "target": 41, "weight": 2.0}, {"source": 27, "target": 42, "weight": 2.741541856482796}, {"source": 27, "target": 43, "weight": 2.0}, {"source": 27, "target": 45, "weight": 2.0}, {"source": 27, "target": 46, "weight": 2.0}, {"source": 27, "target": 47, "weight": 2.0}, {"source": 27, "target": 48, "weight": 2.745267282139416}, {"source": 28, "target": 29, "weight": 2.0}, {"source": 28, "target": 30, "weight": 2.0}, {"source": 28, "target": 31, "weight": 2.0}, {"source": 28, "target": 32, "weight": 2.749943876973178}, {"source": 28, "target": 33, "weight": 3.8330742041942854}, {"source": 28, "target": 34, "weight": 2.0}, {"source": 28, "target": 35, "weight": 2.0}, {"source": 28, "target": 36, "weight": 3.796029383288931}, {"source": 28, "target": 37, "weight": 2.0}, {"source": 28, "target": 38, "weight": 2.0}, {"source": 28, "target": 39, "weight": 2.0}, {"source": 28, "target": 41, "weight": 2.0}, {"source": 28, "target": 42, "weight": 2.0}, {"source": 28, "target": 43, "weight": 2.0}, {"source": 28, "target": 44, "weight": 2.0}, {"source": 28, "target": 45, "weight": 2.0}, {"source": 28, "target": 46, "weight": 2.7468587059612872}, {"source": 28, "target": 47, "weight": 2.0}, {"source": 29, "target": 30, "weight": 2.7482083815577187}, {"source": 29, "target": 31, "weight": 2.751195645199222}, {"source": 29, "target": 32, "weight": 2.0}, {"source": 29, "target": 33, "weight": 2.0}, {"source": 29, "target": 35, "weight": 2.0}, {"source": 29, "target": 37, "weight": 2.0}, {"source": 29, "target": 38, "weight": 2.0}, {"source": 29, "target": 39, "weight": 2.0}, {"source": 29, "target": 40, "weight": 2.0}, {"source": 29, "target": 41, "weight": 2.0}, {"source": 29, "target": 42, "weight": 2.0}, {"source": 29, "target": 43, "weight": 2.0}, {"source": 29, "target": 44, "weight": 2.7521094327512743}, {"source": 29, "target": 45, "weight": 2.0}, {"source": 29, "target": 47, "weight": 2.0}, {"source": 29, "target": 48, "weight": 2.0}, {"source": 29, "target": 49, "weight": 2.7473694393446313}, {"source": 30, "target": 31, "weight": 2.0}, {"source": 30, "target": 32, "weight": 2.0}, {"source": 30, "target": 33, "weight": 2.0}, {"source": 30, "target": 34, "weight": 2.0}, {"source": 30, "target": 35, "weight": 2.0}, {"source": 30, "target": 36, "weight": 2.0}, {"source": 30, "target": 37, "weight": 2.0}, {"source": 30, "target": 38, "weight": 2.0}, {"source": 30, "target": 39, "weight": 2.0}, {"source": 30, "target": 42, "weight": 2.0}, {"source": 30, "target": 43, "weight": 2.0}, {"source": 30, "target": 44, "weight": 2.0}, {"source": 30, "target": 45, "weight": 2.0}, {"source": 30, "target": 46, "weight": 2.0}, {"source": 30, "target": 47, "weight": 2.750807839256413}, {"source": 30, "target": 48, "weight": 2.7448301757336537}, {"source": 30, "target": 49, "weight": 2.0}, {"source": 31, "target": 32, "weight": 2.0}, {"source": 31, "target": 33, "weight": 2.0}, {"source": 31, "target": 35, "weight": 2.0}, {"source": 31, "target": 37, "weight": 2.7461847483000894}, {"source": 31, "target": 38, "weight": 2.0}, {"source": 31, "target": 39, "weight": 2.751525104522463}, {"source": 31, "target": 40, "weight": 2.0}, {"source": 31, "target": 41, "weight": 2.0}, {"source": 31, "target": 42, "weight": 2.0}, {"source": 31, "target": 43, "weight": 2.0}, {"source": 31, "target": 44, "weight": 2.0}, {"source": 31, "target": 46, "weight": 2.0}, {"source": 31, "target": 47, "weight": 2.754233193456621}, {"source": 31, "target": 48, "weight": 2.0}, {"source": 31, "target": 49, "weight": 2.0}, {"source": 32, "target": 34, "weight": 2.0}, {"source": 32, "target": 35, "weight": 2.747673500870485}, {"source": 32, "target": 36, "weight": 2.0}, {"source": 32, "target": 37, "weight": 2.0}, {"source": 32, "target": 38, "weight": 2.7421025056359203}, {"source": 32, "target": 39, "weight": 2.0}, {"source": 32, "target": 41, "weight": 2.7457101284536654}, {"source": 32, "target": 42, "weight": 2.0}, {"source": 32, "target": 43, "weight": 2.0}, {"source": 32, "target": 44, "weight": 2.0}, {"source": 32, "target": 45, "weight": 2.0}, {"source": 32, "target": 46, "weight": 2.0}, {"source": 32, "target": 47, "weight": 2.0}, {"source": 32, "target": 48, "weight": 2.745978475807672}, {"source": 32, "target": 49, "weight": 2.0}, {"source": 33, "target": 34, "weight": 2.0}, {"source": 33, "target": 35, "weight": 2.7489815605420715}, {"source": 33, "target": 36, "weight": 2.7423607520925657}, {"source": 33, "target": 37, "weight": 2.0}, {"source": 33, "target": 38, "weight": 2.0}, {"source": 33, "target": 39, "weight": 2.0}, {"source": 33, "target": 40, "weight": 2.0}, {"source": 33, "target": 41, "weight": 2.0}, {"source": 33, "target": 42, "weight": 2.0}, {"source": 33, "target": 43, "weight": 2.0}, {"source": 33, "target": 44, "weight": 2.0}, {"source": 33, "target": 45, "weight": 2.759923490141011}, {"source": 33, "target": 46, "weight": 2.0}, {"source": 33, "target": 47, "weight": 2.0}, {"source": 33, "target": 48, "weight": 2.0}, {"source": 33, "target": 49, "weight": 2.0}, {"source": 34, "target": 35, "weight": 2.0}, {"source": 34, "target": 36, "weight": 2.0}, {"source": 34, "target": 37, "weight": 2.0}, {"source": 34, "target": 39, "weight": 2.0}, {"source": 34, "target": 41, "weight": 2.0}, {"source": 34, "target": 42, "weight": 2.0}, {"source": 34, "target": 43, "weight": 2.0}, {"source": 34, "target": 44, "weight": 2.0}, {"source": 34, "target": 45, "weight": 2.0}, {"source": 34, "target": 46, "weight": 2.756015951678176}, {"source": 34, "target": 47, "weight": 2.0}, {"source": 34, "target": 48, "weight": 2.0}, {"source": 34, "target": 49, "weight": 2.0}, {"source": 35, "target": 36, "weight": 2.738095127335677}, {"source": 35, "target": 37, "weight": 2.0}, {"source": 35, "target": 38, "weight": 2.0}, {"source": 35, "target": 39, "weight": 2.0}, {"source": 35, "target": 42, "weight": 3.788497598005619}, {"source": 35, "target": 43, "weight": 2.0}, {"source": 35, "target": 44, "weight": 2.0}, {"source": 35, "target": 45, "weight": 2.0}, {"source": 35, "target": 46, "weight": 2.0}, {"source": 35, "target": 47, "weight": 2.0}, {"source": 35, "target": 48, "weight": 2.7455162800380144}, {"source": 35, "target": 49, "weight": 2.0}, {"source": 36, "target": 37, "weight": 2.0}, {"source": 36, "target": 38, "weight": 2.0}, {"source": 36, "target": 39, "weight": 2.0}, {"source": 36, "target": 40, "weight": 2.732056353727465}, {"source": 36, "target": 41, "weight": 2.0}, {"source": 36, "target": 42, "weight": 2.0}, {"source": 36, "target": 43, "weight": 2.0}, {"source": 36, "target": 44, "weight": 2.0}, {"source": 36, "target": 45, "weight": 2.0}, {"source": 36, "target": 46, "weight": 2.0}, {"source": 36, "target": 48, "weight": 2.7389716833000386}, {"source": 36, "target": 49, "weight": 2.7402533122645254}, {"source": 37, "target": 38, "weight": 2.0}, {"source": 37, "target": 39, "weight": 2.0}, {"source": 37, "target": 40, "weight": 2.0}, {"source": 37, "target": 41, "weight": 2.0}, {"source": 37, "target": 42, "weight": 2.0}, {"source": 37, "target": 43, "weight": 2.0}, {"source": 37, "target": 44, "weight": 2.0}, {"source": 37, "target": 45, "weight": 2.7564526107173606}, {"source": 37, "target": 46, "weight": 2.749550144899142}, {"source": 37, "target": 47, "weight": 2.0}, {"source": 37, "target": 48, "weight": 2.7441879624260768}, {"source": 37, "target": 49, "weight": 2.0}, {"source": 38, "target": 39, "weight": 2.0}, {"source": 38, "target": 40, "weight": 2.0}, {"source": 38, "target": 41, "weight": 2.0}, {"source": 38, "target": 42, "weight": 2.0}, {"source": 38, "target": 43, "weight": 2.0}, {"source": 38, "target": 44, "weight": 2.0}, {"source": 38, "target": 45, "weight": 2.0}, {"source": 38, "target": 46, "weight": 2.0}, {"source": 38, "target": 48, "weight": 2.0}, {"source": 38, "target": 49, "weight": 2.0}, {"source": 39, "target": 40, "weight": 2.0}, {"source": 39, "target": 41, "weight": 2.7512577323859757}, {"source": 39, "target": 42, "weight": 2.0}, {"source": 39, "target": 43, "weight": 2.0}, {"source": 39, "target": 44, "weight": 2.0}, {"source": 39, "target": 46, "weight": 2.0}, {"source": 39, "target": 49, "weight": 2.0}, {"source": 40, "target": 42, "weight": 3.7750370633871673}, {"source": 40, "target": 44, "weight": 2.0}, {"source": 40, "target": 45, "weight": 2.0}, {"source": 40, "target": 46, "weight": 2.0}, {"source": 40, "target": 47, "weight": 3.8183319545645977}, {"source": 40, "target": 48, "weight": 2.7409376405688377}, {"source": 40, "target": 49, "weight": 2.743531660445203}, {"source": 41, "target": 42, "weight": 2.7334722101899436}, {"source": 41, "target": 43, "weight": 3.816553918411766}, {"source": 41, "target": 46, "weight": 2.0}, {"source": 41, "target": 47, "weight": 2.0}, {"source": 41, "target": 48, "weight": 2.0}, {"source": 41, "target": 49, "weight": 2.0}, {"source": 42, "target": 43, "weight": 2.0}, {"source": 42, "target": 44, "weight": 2.0}, {"source": 42, "target": 45, "weight": 2.7509169411284446}, {"source": 42, "target": 46, "weight": 2.0}, {"source": 42, "target": 47, "weight": 2.0}, {"source": 42, "target": 48, "weight": 2.0}, {"source": 42, "target": 49, "weight": 2.0}, {"source": 43, "target": 44, "weight": 2.0}, {"source": 43, "target": 45, "weight": 2.0}, {"source": 43, "target": 48, "weight": 2.7468167183777163}, {"source": 43, "target": 49, "weight": 2.748766192112712}, {"source": 44, "target": 46, "weight": 2.0}, {"source": 44, "target": 47, "weight": 2.0}, {"source": 44, "target": 48, "weight": 2.0}, {"source": 44, "target": 49, "weight": 2.0}, {"source": 45, "target": 48, "weight": 2.0}, {"source": 45, "target": 49, "weight": 2.0}, {"source": 46, "target": 47, "weight": 2.0}, {"source": 46, "target": 49, "weight": 2.74844675580946}, {"source": 47, "target": 48, "weight": 2.0}, {"source": 47, "target": 49, "weight": 2.0}, {"source": 48, "target": 49, "weight": 2.0}, {"source": 50, "target": 51, "weight": 2.0}, {"source": 50, "target": 52, "weight": 2.0}, {"source": 50, "target": 53, "weight": 2.0}, {"source": 50, "target": 54, "weight": 2.0}, {"source": 50, "target": 56, "weight": 2.0}, {"source": 50, "target": 57, "weight": 2.0}, {"source": 50, "target": 58, "weight": 2.74291747449733}, {"source": 50, "target": 59, "weight": 2.0}, {"source": 50, "target": 60, "weight": 2.0}, {"source": 50, "target": 61, "weight": 2.0}, {"source": 50, "target": 62, "weight": 2.7383564725950214}, {"source": 50, "target": 63, "weight": 2.0}, {"source": 50, "target": 64, "weight": 2.7373032032992413}, {"source": 50, "target": 65, "weight": 2.0}, {"source": 50, "target": 66, "weight": 2.0}, {"source": 50, "target": 67, "weight": 2.0}, {"source": 50, "target": 68, "weight": 2.0}, {"source": 50, "target": 69, "weight": 2.7441411316474067}, {"source": 50, "target": 71, "weight": 2.0}, {"source": 50, "target": 72, "weight": 2.0}, {"source": 50, "target": 73, "weight": 2.0}, {"source": 50, "target": 74, "weight": 2.7408612807313486}, {"source": 51, "target": 52, "weight": 2.0}, {"source": 51, "target": 53, "weight": 2.0}, {"source": 51, "target": 54, "weight": 2.0}, {"source": 51, "target": 55, "weight": 2.0}, {"source": 51, "target": 56, "weight": 2.0}, {"source": 51, "target": 57, "weight": 2.0}, {"source": 51, "target": 58, "weight": 2.0}, {"source": 51, "target": 59, "weight": 3.8255258441709143}, {"source": 51, "target": 60, "weight": 2.7456235141560406}, {"source": 51, "target": 61, "weight": 2.0}, {"source": 51, "target": 62, "weight": 2.0}, {"source": 51, "target": 63, "weight": 2.73973833757498}, {"source": 51, "target": 64, "weight": 2.0}, {"source": 51, "target": 65, "weight": 2.0}, {"source": 51, "target": 66, "weight": 2.0}, {"source": 51, "target": 67, "weight": 2.0}, {"source": 51, "target": 69, "weight": 2.0}, {"source": 51, "target": 70, "weight": 2.0}, {"source": 51, "target": 71, "weight": 2.0}, {"source": 51, "target": 72, "weight": 2.0}, {"source": 51, "target": 73, "weight": 2.0}, {"source": 51, "target": 74, "weight": 2.0}, {"source": 52, "target": 53, "weight": 2.0}, {"source": 52, "target": 54, "weight": 2.7426402576989566}, {"source": 52, "target": 55, "weight": 2.0}, {"source": 52, "target": 56, "weight": 2.0}, {"source": 52, "target": 57, "weight": 2.0}, {"source": 52, "target": 58, "weight": 2.0}, {"source": 52, "target": 61, "weight": 2.0}, {"source": 52, "target": 62, "weight": 2.0}, {"source": 52, "target": 63, "weight": 2.0}, {"source": 52, "target": 64, "weight": 2.0}, {"source": 52, "target": 65, "weight": 2.0}, {"source": 52, "target": 66, "weight": 2.0}, {"source": 52, "target": 69, "weight": 2.747400657696789}, {"source": 52, "target": 70, "weight": 2.0}, {"source": 52, "target": 71, "weight": 2.0}, {"source": 52, "target": 72, "weight": 2.0}, {"source": 52, "target": 73, "weight": 2.0}, {"source": 53, "target": 54, "weight": 2.0}, {"source": 53, "target": 55, "weight": 2.0}, {"source": 53, "target": 57, "weight": 2.0}, {"source": 53, "target": 58, "weight": 2.0}, {"source": 53, "target": 59, "weight": 2.0}, {"source": 53, "target": 60, "weight": 2.0}, {"source": 53, "target": 61, "weight": 2.0}, {"source": 53, "target": 62, "weight": 2.0}, {"source": 53, "target": 63, "weight": 2.0}, {"source": 53, "target": 64, "weight": 2.0}, {"source": 53, "target": 67, "weight": 2.7557480907531247}, {"source": 53, "target": 68, "weight": 2.0}, {"source": 53, "target": 69, "weight": 2.0}, {"source": 53, "target": 70, "weight": 2.0}, {"source": 53, "target": 71, "weight": 2.7462686567164183}, {"source": 53, "target": 72, "weight": 2.0}, {"source": 53, "target": 73, "weight": 2.0}, {"source": 53, "target": 74, "weight": 2.0}, {"source": 54, "target": 55, "weight": 2.0}, {"source": 54, "target": 56, "weight": 2.0}, {"source": 54, "target": 57, "weight": 2.0}, {"source": 54, "target": 58, "weight": 2.0}, {"source": 54, "target": 59, "weight": 2.0}, {"source": 54, "target": 60, "weight": 2.0}, {"source": 54, "target": 61, "weight": 2.0}, {"source": 54, "target": 62, "weight": 2.0}, {"source": 54, "target": 63, "weight": 2.7399003038522607}, {"source": 54, "target": 64, "weight": 2.0}, {"source": 54, "target": 65, "weight": 2.0}, {"source": 54, "target": 66, "weight": 2.0}, {"source": 54, "target": 67, "weight": 2.0}, {"source": 54, "target": 68, "weight": 2.0}, {"source": 54, "target": 69, "weight": 2.7462364686135023}, {"source": 54, "target": 70, "weight": 2.0}, {"source": 54, "target": 71, "weight": 2.0}, {"source": 54, "target": 72, "weight": 2.0}, {"source": 54, "target": 73, "weight": 2.0}, {"source": 54, "target": 74, "weight": 2.0}, {"source": 55, "target": 56, "weight": 2.7473047577098666}, {"source": 55, "target": 57, "weight": 2.0}, {"source": 55, "target": 58, "weight": 2.0}, {"source": 55, "target": 59, "weight": 2.0}, {"source": 55, "target": 60, "weight": 2.0}, {"source": 55, "target": 61, "weight": 2.7500922244330956}, {"source": 55, "target": 62, "weight": 2.0}, {"source": 55, "target": 63, "weight": 2.0}, {"source": 55, "target": 64, "weight": 2.7457780161330403}, {"source": 55, "target": 65, "weight": 2.7437127261376255}, {"source": 55, "target": 66, "weight": 2.0}, {"source": 55, "target": 67, "weight": 2.0}, {"source": 55, "target": 68, "weight": 2.0}, {"source": 55, "target": 69, "weight": 2.0}, {"source": 55, "target": 70, "weight": 2.0}, {"source": 55, "target": 71, "weight": 2.0}, {"source": 55, "target": 73, "weight": 2.0}, {"source": 55, "target": 74, "weight": 2.0}, {"source": 56, "target": 57, "weight": 2.0}, {"source": 56, "target": 59, "weight": 2.7471196345709523}, {"source": 56, "target": 60, "weight": 2.0}, {"source": 56, "target": 61, "weight": 2.0}, {"source": 56, "target": 62, "weight": 2.74749516188518}, {"source": 56, "target": 63, "weight": 2.0}, {"source": 56, "target": 65, "weight": 2.7393619621192102}, {"source": 56, "target": 66, "weight": 2.0}, {"source": 56, "target": 67, "weight": 2.748263114842645}, {"source": 56, "target": 68, "weight": 2.0}, {"source": 56, "target": 69, "weight": 2.0}, {"source": 56, "target": 70, "weight": 2.0}, {"source": 56, "target": 71, "weight": 2.0}, {"source": 56, "target": 72, "weight": 2.0}, {"source": 56, "target": 73, "weight": 2.0}, {"source": 56, "target": 74, "weight": 2.747406313683021}, {"source": 57, "target": 58, "weight": 2.0}, {"source": 57, "target": 59, "weight": 2.0}, {"source": 57, "target": 60, "weight": 2.0}, {"source": 57, "target": 61, "weight": 2.0}, {"source": 57, "target": 62, "weight": 2.7496856943550347}, {"source": 57, "target": 63, "weight": 2.0}, {"source": 57, "target": 64, "weight": 2.0}, {"source": 57, "target": 65, "weight": 2.0}, {"source": 57, "target": 67, "weight": 2.0}, {"source": 57, "target": 69, "weight": 3.8366001270842003}, {"source": 57, "target": 70, "weight": 2.0}, {"source": 57, "target": 71, "weight": 2.0}, {"source": 57, "target": 72, "weight": 2.7483018893443396}, {"source": 57, "target": 74, "weight": 2.0}, {"source": 58, "target": 59, "weight": 2.752299224978703}, {"source": 58, "target": 60, "weight": 2.0}, {"source": 58, "target": 61, "weight": 2.0}, {"source": 58, "target": 62, "weight": 2.0}, {"source": 58, "target": 63, "weight": 2.0}, {"source": 58, "target": 64, "weight": 2.0}, {"source": 58, "target": 65, "weight": 2.739698595048348}, {"source": 58, "target": 66, "weight": 2.7564746545514507}, {"source": 58, "target": 67, "weight": 2.0}, {"source": 58, "target": 68, "weight": 2.0}, {"source": 58, "target": 71, "weight": 2.0}, {"source": 58, "target": 72, "weight": 2.0}, {"source": 58, "target": 73, "weight": 2.0}, {"source": 58, "target": 74, "weight": 2.0}, {"source": 59, "target": 60, "weight": 2.0}, {"source": 59, "target": 62, "weight": 2.0}, {"source": 59, "target": 63, "weight": 2.0}, {"source": 59, "target": 64, "weight": 2.7482744878529206}, {"source": 59, "target": 65, "weight": 2.0}, {"source": 59, "target": 66, "weight": 2.7564420921309227}, {"source": 59, "target": 67, "weight": 2.0}, {"source": 59, "target": 68, "weight": 2.0}, {"source": 59, "target": 70, "weight": 2.0}, {"source": 59, "target": 71, "weight": 2.0}, {"source": 59, "target": 72, "weight": 2.0}, {"source": 59, "target": 73, "weight": 2.0}, {"source": 59, "target": 74, "weight": 2.0}, {"source": 60, "target": 61, "weight": 2.0}, {"source": 60, "target": 62, "weight": 2.0}, {"source": 60, "target": 63, "weight": 2.0}, {"source": 60, "target": 64, "weight": 2.746268656716418}, {"source": 60, "target": 65, "weight": 2.0}, {"source": 60, "target": 66, "weight": 2.0}, {"source": 60, "target": 67, "weight": 2.0}, {"source": 60, "target": 68, "weight": 2.0}, {"source": 60, "target": 69, "weight": 2.0}, {"source": 60, "target": 71, "weight": 2.0}, {"source": 60, "target": 72, "weight": 2.7428195133756423}, {"source": 60, "target": 73, "weight": 2.748759736904461}, {"source": 60, "target": 74, "weight": 2.0}, {"source": 61, "target": 62, "weight": 3.818393820032112}, {"source": 61, "target": 63, "weight": 2.0}, {"source": 61, "target": 64, "weight": 2.0}, {"source": 61, "target": 65, "weight": 2.740506093093675}, {"source": 61, "target": 66, "weight": 2.0}, {"source": 61, "target": 67, "weight": 2.0}, {"source": 61, "target": 68, "weight": 2.0}, {"source": 61, "target": 69, "weight": 2.0}, {"source": 61, "target": 70, "weight": 2.0}, {"source": 61, "target": 71, "weight": 2.0}, {"source": 61, "target": 72, "weight": 2.0}, {"source": 61, "target": 73, "weight": 2.0}, {"source": 61, "target": 74, "weight": 2.0}, {"source": 62, "target": 63, "weight": 2.0}, {"source": 62, "target": 64, "weight": 2.7461647751336145}, {"source": 62, "target": 65, "weight": 2.7383108281729878}, {"source": 62, "target": 66, "weight": 2.0}, {"source": 62, "target": 67, "weight": 2.0}, {"source": 62, "target": 68, "weight": 2.0}, {"source": 62, "target": 69, "weight": 2.0}, {"source": 62, "target": 70, "weight": 2.0}, {"source": 62, "target": 71, "weight": 2.0}, {"source": 62, "target": 73, "weight": 2.0}, {"source": 62, "target": 74, "weight": 2.0}, {"source": 63, "target": 64, "weight": 2.0}, {"source": 63, "target": 65, "weight": 3.7612734802540593}, {"source": 63, "target": 66, "weight": 2.0}, {"source": 63, "target": 67, "weight": 2.0}, {"source": 63, "target": 68, "weight": 2.0}, {"source": 63, "target": 69, "weight": 2.0}, {"source": 63, "target": 70, "weight": 2.0}, {"source": 63, "target": 71, "weight": 2.0}, {"source": 63, "target": 73, "weight": 2.0}, {"source": 63, "target": 74, "weight": 2.0}, {"source": 64, "target": 66, "weight": 2.0}, {"source": 64, "target": 67, "weight": 2.0}, {"source": 64, "target": 68, "weight": 2.749409204746353}, {"source": 64, "target": 69, "weight": 2.0}, {"source": 64, "target": 70, "weight": 2.0}, {"source": 64, "target": 71, "weight": 2.745385343583016}, {"source": 64, "target": 72, "weight": 2.0}, {"source": 64, "target": 73, "weight": 2.0}, {"source": 64, "target": 74, "weight": 2.0}, {"source": 65, "target": 67, "weight": 2.0}, {"source": 65, "target": 68, "weight": 3.802445423045162}, {"source": 65, "target": 69, "weight": 2.0}, {"source": 65, "target": 70, "weight": 2.0}, {"source": 65, "target": 71, "weight": 2.0}, {"source": 65, "target": 72, "weight": 2.0}, {"source": 65, "target": 73, "weight": 2.7419096311774678}, {"source": 65, "target": 74, "weight": 2.0}, {"source": 66, "target": 68, "weight": 2.0}, {"source": 66, "target": 69, "weight": 2.0}, {"source": 66, "target": 70, "weight": 2.0}, {"source": 66, "target": 71, "weight": 2.0}, {"source": 66, "target": 72, "weight": 2.0}, {"source": 66, "target": 73, "weight": 2.0}, {"source": 66, "target": 74, "weight": 2.0}, {"source": 67, "target": 68, "weight": 2.0}, {"source": 67, "target": 69, "weight": 2.0}, {"source": 67, "target": 70, "weight": 2.0}, {"source": 67, "target": 71, "weight": 2.0}, {"source": 67, "target": 72, "weight": 2.0}, {"source": 67, "target": 73, "weight": 2.0}, {"source": 67, "target": 74, "weight": 2.0}, {"source": 68, "target": 69, "weight": 2.0}, {"source": 68, "target": 70, "weight": 2.0}, {"source": 68, "target": 71, "weight": 2.0}, {"source": 68, "target": 72, "weight": 2.0}, {"source": 68, "target": 73, "weight": 2.0}, {"source": 68, "target": 74, "weight": 2.0}, {"source": 69, "target": 70, "weight": 2.0}, {"source": 69, "target": 71, "weight": 2.0}, {"source": 69, "target": 72, "weight": 2.0}, {"source": 69, "target": 73, "weight": 2.0}, {"source": 69, "target": 74, "weight": 2.0}, {"source": 70, "target": 71, "weight": 2.0}, {"source": 70, "target": 72, "weight": 2.0}, {"source": 70, "target": 73, "weight": 2.7508742772016865}, {"source": 70, "target": 74, "weight": 2.746268656716418}, {"source": 71, "target": 72, "weight": 2.0}, {"source": 71, "target": 73, "weight": 2.0}, {"source": 71, "target": 74, "weight": 2.0}, {"source": 72, "target": 73, "weight": 2.0}, {"source": 72, "target": 74, "weight": 2.0}, {"source": 75, "target": 76, "weight": 2.0}, {"source": 75, "target": 77, "weight": 2.0}, {"source": 75, "target": 78, "weight": 2.0}, {"source": 75, "target": 79, "weight": 2.0}, {"source": 75, "target": 81, "weight": 2.7475017438769123}, {"source": 75, "target": 82, "weight": 2.0}, {"source": 75, "target": 83, "weight": 2.0}, {"source": 75, "target": 84, "weight": 2.747849005297898}, {"source": 75, "target": 85, "weight": 2.7446061373364707}, {"source": 75, "target": 86, "weight": 2.0}, {"source": 75, "target": 87, "weight": 2.0}, {"source": 75, "target": 88, "weight": 2.746796416886907}, {"source": 75, "target": 89, "weight": 2.0}, {"source": 75, "target": 90, "weight": 2.0}, {"source": 75, "target": 91, "weight": 2.0}, {"source": 75, "target": 92, "weight": 2.7461045834705557}, {"source": 75, "target": 94, "weight": 2.752108147941251}, {"source": 75, "target": 95, "weight": 2.0}, {"source": 75, "target": 96, "weight": 2.0}, {"source": 76, "target": 77, "weight": 2.744391882605609}, {"source": 76, "target": 78, "weight": 2.0}, {"source": 76, "target": 79, "weight": 2.0}, {"source": 76, "target": 80, "weight": 2.0}, {"source": 76, "target": 81, "weight": 2.0}, {"source": 76, "target": 82, "weight": 2.0}, {"source": 76, "target": 83, "weight": 2.0}, {"source": 76, "target": 84, "weight": 2.0}, {"source": 76, "target": 85, "weight": 2.0}, {"source": 76, "target": 86, "weight": 2.0}, {"source": 76, "target": 87, "weight": 2.0}, {"source": 76, "target": 88, "weight": 2.0}, {"source": 76, "target": 89, "weight": 2.0}, {"source": 76, "target": 90, "weight": 2.7455165570745885}, {"source": 76, "target": 91, "weight": 2.0}, {"source": 76, "target": 92, "weight": 2.0}, {"source": 76, "target": 93, "weight": 2.0}, {"source": 76, "target": 94, "weight": 2.75559920461377}, {"source": 76, "target": 95, "weight": 2.0}, {"source": 76, "target": 96, "weight": 2.0}, {"source": 76, "target": 97, "weight": 2.0}, {"source": 76, "target": 98, "weight": 2.0}, {"source": 76, "target": 99, "weight": 2.0}, {"source": 77, "target": 78, "weight": 2.0}, {"source": 77, "target": 79, "weight": 2.0}, {"source": 77, "target": 80, "weight": 2.0}, {"source": 77, "target": 81, "weight": 2.0}, {"source": 77, "target": 82, "weight": 2.7491296874212976}, {"source": 77, "target": 83, "weight": 2.0}, {"source": 77, "target": 84, "weight": 2.746220235583257}, {"source": 77, "target": 85, "weight": 2.0}, {"source": 77, "target": 86, "weight": 2.0}, {"source": 77, "target": 87, "weight": 2.0}, {"source": 77, "target": 88, "weight": 2.0}, {"source": 77, "target": 89, "weight": 2.0}, {"source": 77, "target": 90, "weight": 2.0}, {"source": 77, "target": 91, "weight": 2.0}, {"source": 77, "target": 92, "weight": 2.0}, {"source": 77, "target": 93, "weight": 2.0}, {"source": 77, "target": 94, "weight": 2.0}, {"source": 77, "target": 95, "weight": 2.744979351086981}, {"source": 77, "target": 96, "weight": 2.746268656716418}, {"source": 77, "target": 97, "weight": 2.0}, {"source": 77, "target": 98, "weight": 2.0}, {"source": 77, "target": 99, "weight": 2.0}, {"source": 78, "target": 79, "weight": 2.0}, {"source": 78, "target": 80, "weight": 2.739902181895844}, {"source": 78, "target": 81, "weight": 2.0}, {"source": 78, "target": 82, "weight": 2.0}, {"source": 78, "target": 83, "weight": 2.0}, {"source": 78, "target": 84, "weight": 2.742825630167321}, {"source": 78, "target": 85, "weight": 2.0}, {"source": 78, "target": 86, "weight": 2.0}, {"source": 78, "target": 87, "weight": 2.740374421308369}, {"source": 78, "target": 88, "weight": 2.0}, {"source": 78, "target": 89, "weight": 2.0}, {"source": 78, "target": 90, "weight": 2.7384252233719346}, {"source": 78, "target": 91, "weight": 2.7315500959142085}, {"source": 78, "target": 92, "weight": 2.7402990738794175}, {"source": 78, "target": 93, "weight": 2.0}, {"source": 78, "target": 95, "weight": 2.0}, {"source": 78, "target": 96, "weight": 2.0}, {"source": 78, "target": 97, "weight": 2.0}, {"source": 78, "target": 98, "weight": 2.0}, {"source": 78, "target": 99, "weight": 2.0}, {"source": 79, "target": 80, "weight": 2.0}, {"source": 79, "target": 81, "weight": 2.0}, {"source": 79, "target": 82, "weight": 2.0}, {"source": 79, "target": 83, "weight": 2.0}, {"source": 79, "target": 85, "weight": 2.0}, {"source": 79, "target": 86, "weight": 2.0}, {"source": 79, "target": 87, "weight": 2.0}, {"source": 79, "target": 88, "weight": 2.0}, {"source": 79, "target": 89, "weight": 2.0}, {"source": 79, "target": 90, "weight": 2.7417829239693274}, {"source": 79, "target": 91, "weight": 2.0}, {"source": 79, "target": 92, "weight": 2.0}, {"source": 79, "target": 93, "weight": 2.0}, {"source": 79, "target": 94, "weight": 2.753076913199858}, {"source": 79, "target": 95, "weight": 2.0}, {"source": 79, "target": 96, "weight": 2.0}, {"source": 79, "target": 97, "weight": 2.0}, {"source": 79, "target": 98, "weight": 2.7411013513350726}, {"source": 79, "target": 99, "weight": 2.0}, {"source": 80, "target": 81, "weight": 2.0}, {"source": 80, "target": 82, "weight": 2.0}, {"source": 80, "target": 83, "weight": 2.0}, {"source": 80, "target": 84, "weight": 2.0}, {"source": 80, "target": 85, "weight": 2.0}, {"source": 80, "target": 86, "weight": 2.0}, {"source": 80, "target": 87, "weight": 2.0}, {"source": 80, "target": 88, "weight": 2.0}, {"source": 80, "target": 89, "weight": 2.0}, {"source": 80, "target": 90, "weight": 2.747401638136191}, {"source": 80, "target": 91, "weight": 2.0}, {"source": 80, "target": 92, "weight": 2.0}, {"source": 80, "target": 93, "weight": 2.0}, {"source": 80, "target": 94, "weight": 2.0}, {"source": 80, "target": 95, "weight": 2.0}, {"source": 80, "target": 96, "weight": 2.0}, {"source": 80, "target": 97, "weight": 2.7449834931761945}, {"source": 80, "target": 99, "weight": 2.743843538016703}, {"source": 81, "target": 82, "weight": 2.0}, {"source": 81, "target": 83, "weight": 2.0}, {"source": 81, "target": 84, "weight": 2.0}, {"source": 81, "target": 85, "weight": 2.0}, {"source": 81, "target": 86, "weight": 2.0}, {"source": 81, "target": 87, "weight": 2.7443591845732414}, {"source": 81, "target": 88, "weight": 2.0}, {"source": 81, "target": 89, "weight": 2.0}, {"source": 81, "target": 90, "weight": 2.0}, {"source": 81, "target": 91, "weight": 2.0}, {"source": 81, "target": 92, "weight": 2.744227814697437}, {"source": 81, "target": 93, "weight": 2.0}, {"source": 81, "target": 94, "weight": 2.0}, {"source": 81, "target": 95, "weight": 2.7424612422132015}, {"source": 81, "target": 96, "weight": 2.0}, {"source": 81, "target": 97, "weight": 2.0}, {"source": 81, "target": 98, "weight": 2.743655689347439}, {"source": 81, "target": 99, "weight": 2.0}, {"source": 82, "target": 83, "weight": 2.0}, {"source": 82, "target": 84, "weight": 2.0}, {"source": 82, "target": 85, "weight": 2.0}, {"source": 82, "target": 86, "weight": 2.0}, {"source": 82, "target": 88, "weight": 2.746846604093249}, {"source": 82, "target": 89, "weight": 2.7413029464334473}, {"source": 82, "target": 90, "weight": 2.75018175753293}, {"source": 82, "target": 94, "weight": 2.7539927453789965}, {"source": 82, "target": 95, "weight": 2.746922614908832}, {"source": 82, "target": 96, "weight": 2.0}, {"source": 82, "target": 97, "weight": 2.0}, {"source": 82, "target": 98, "weight": 2.0}, {"source": 82, "target": 99, "weight": 2.0}, {"source": 83, "target": 84, "weight": 2.0}, {"source": 83, "target": 85, "weight": 2.0}, {"source": 83, "target": 86, "weight": 2.0}, {"source": 83, "target": 87, "weight": 2.0}, {"source": 83, "target": 88, "weight": 2.0}, {"source": 83, "target": 89, "weight": 2.0}, {"source": 83, "target": 91, "weight": 2.0}, {"source": 83, "target": 92, "weight": 2.0}, {"source": 83, "target": 93, "weight": 2.0}, {"source": 83, "target": 95, "weight": 2.7466062578547237}, {"source": 83, "target": 96, "weight": 2.0}, {"source": 83, "target": 97, "weight": 2.744998787088616}, {"source": 83, "target": 98, "weight": 2.0}, {"source": 83, "target": 99, "weight": 2.0}, {"source": 84, "target": 85, "weight": 2.0}, {"source": 84, "target": 86, "weight": 2.0}, {"source": 84, "target": 87, "weight": 2.0}, {"source": 84, "target": 88, "weight": 2.0}, {"source": 84, "target": 89, "weight": 2.0}, {"source": 84, "target": 90, "weight": 2.0}, {"source": 84, "target": 91, "weight": 2.0}, {"source": 84, "target": 92, "weight": 2.0}, {"source": 84, "target": 93, "weight": 2.0}, {"source": 84, "target": 94, "weight": 2.0}, {"source": 84, "target": 95, "weight": 2.0}, {"source": 84, "target": 96, "weight": 2.7455201638992777}, {"source": 84, "target": 97, "weight": 2.0}, {"source": 84, "target": 98, "weight": 2.0}, {"source": 84, "target": 99, "weight": 2.0}, {"source": 85, "target": 86, "weight": 2.0}, {"source": 85, "target": 87, "weight": 3.8079371426237243}, {"source": 85, "target": 88, "weight": 2.0}, {"source": 85, "target": 89, "weight": 3.784489146289234}, {"source": 85, "target": 90, "weight": 2.0}, {"source": 85, "target": 91, "weight": 2.0}, {"source": 85, "target": 92, "weight": 2.0}, {"source": 85, "target": 93, "weight": 2.0}, {"source": 85, "target": 94, "weight": 2.0}, {"source": 85, "target": 95, "weight": 2.7462686567164183}, {"source": 85, "target": 96, "weight": 2.0}, {"source": 85, "target": 97, "weight": 2.0}, {"source": 85, "target": 98, "weight": 2.0}, {"source": 85, "target": 99, "weight": 2.0}, {"source": 86, "target": 87, "weight": 2.0}, {"source": 86, "target": 88, "weight": 2.0}, {"source": 86, "target": 90, "weight": 2.0}, {"source": 86, "target": 91, "weight": 2.0}, {"source": 86, "target": 92, "weight": 2.0}, {"source": 86, "target": 93, "weight": 2.0}, {"source": 86, "target": 94, "weight": 2.7481969156349444}, {"source": 86, "target": 95, "weight": 2.0}, {"source": 86, "target": 96, "weight": 2.0}, {"source": 86, "target": 98, "weight": 2.0}, {"source": 86, "target": 99, "weight": 2.0}, {"source": 87, "target": 88, "weight": 2.0}, {"source": 87, "target": 89, "weight": 2.0}, {"source": 87, "target": 90, "weight": 2.743590273085689}, {"source": 87, "target": 91, "weight": 2.73836141272243}, {"source": 87, "target": 92, "weight": 2.0}, {"source": 87, "target": 93, "weight": 2.0}, {"source": 87, "target": 94, "weight": 2.0}, {"source": 87, "target": 95, "weight": 2.0}, {"source": 87, "target": 96, "weight": 2.0}, {"source": 87, "target": 97, "weight": 2.0}, {"source": 87, "target": 98, "weight": 2.0}, {"source": 87, "target": 99, "weight": 2.7411039876872496}, {"source": 88, "target": 89, "weight": 2.0}, {"source": 88, "target": 91, "weight": 2.0}, {"source": 88, "target": 92, "weight": 2.0}, {"source": 88, "target": 93, "weight": 2.0}, {"source": 88, "target": 94, "weight": 2.0}, {"source": 88, "target": 95, "weight": 2.0}, {"source": 88, "target": 96, "weight": 2.746044691423962}, {"source": 88, "target": 97, "weight": 2.0}, {"source": 88, "target": 98, "weight": 2.0}, {"source": 88, "target": 99, "weight": 2.74562722808545}, {"source": 89, "target": 90, "weight": 2.0}, {"source": 89, "target": 91, "weight": 2.7306459263067167}, {"source": 89, "target": 92, "weight": 2.0}, {"source": 89, "target": 93, "weight": 2.0}, {"source": 89, "target": 94, "weight": 2.0}, {"source": 89, "target": 95, "weight": 2.0}, {"source": 89, "target": 96, "weight": 2.0}, {"source": 89, "target": 97, "weight": 2.0}, {"source": 89, "target": 98, "weight": 2.739695200113625}, {"source": 89, "target": 99, "weight": 2.7403771424110017}, {"source": 90, "target": 91, "weight": 2.0}, {"source": 90, "target": 92, "weight": 2.0}, {"source": 90, "target": 93, "weight": 2.0}, {"source": 90, "target": 94, "weight": 2.0}, {"source": 90, "target": 95, "weight": 2.0}, {"source": 90, "target": 96, "weight": 2.0}, {"source": 90, "target": 97, "weight": 2.0}, {"source": 90, "target": 98, "weight": 2.0}, {"source": 90, "target": 99, "weight": 2.0}, {"source": 91, "target": 92, "weight": 2.0}, {"source": 91, "target": 93, "weight": 2.0}, {"source": 91, "target": 94, "weight": 2.0}, {"source": 91, "target": 95, "weight": 2.0}, {"source": 91, "target": 96, "weight": 2.0}, {"source": 91, "target": 97, "weight": 2.7444204697643446}, {"source": 91, "target": 98, "weight": 2.7403751233958538}, {"source": 91, "target": 99, "weight": 2.0}, {"source": 92, "target": 94, "weight": 2.0}, {"source": 92, "target": 95, "weight": 2.0}, {"source": 92, "target": 96, "weight": 2.0}, {"source": 92, "target": 97, "weight": 2.0}, {"source": 92, "target": 98, "weight": 3.812312469873427}, {"source": 92, "target": 99, "weight": 2.743168360752598}, {"source": 93, "target": 94, "weight": 2.0}, {"source": 93, "target": 95, "weight": 2.7416087553427726}, {"source": 93, "target": 96, "weight": 2.0}, {"source": 93, "target": 97, "weight": 2.0}, {"source": 93, "target": 98, "weight": 2.0}, {"source": 93, "target": 99, "weight": 2.0}, {"source": 94, "target": 99, "weight": 2.0}, {"source": 95, "target": 96, "weight": 2.0}, {"source": 95, "target": 97, "weight": 2.0}, {"source": 95, "target": 98, "weight": 2.0}, {"source": 95, "target": 99, "weight": 2.0}, {"source": 96, "target": 97, "weight": 2.0}, {"source": 96, "target": 98, "weight": 2.0}, {"source": 96, "target": 99, "weight": 2.743751530490389}, {"source": 97, "target": 98, "weight": 2.0}, {"source": 97, "target": 99, "weight": 2.0}, {"source": 98, "target": 99, "weight": 2.0}, {"source": 7, "target": 42, "weight": 1.0}, {"source": 7, "target": 36, "weight": 1.0}, {"source": 7, "target": 41, "weight": 1.3606261122587389}, {"source": 7, "target": 38, "weight": 1.0}, {"source": 21, "target": 42, "weight": 1.0}, {"source": 21, "target": 36, "weight": 1.0}, {"source": 21, "target": 41, "weight": 1.0}, {"source": 3, "target": 42, "weight": 1.0}, {"source": 3, "target": 36, "weight": 1.0}, {"source": 3, "target": 40, "weight": 1.0}, {"source": 3, "target": 41, "weight": 1.0}, {"source": 3, "target": 38, "weight": 1.0}, {"source": 14, "target": 42, "weight": 1.3602367279477725}, {"source": 14, "target": 36, "weight": 1.3607140915797724}, {"source": 14, "target": 40, "weight": 1.0}, {"source": 14, "target": 41, "weight": 1.0}, {"source": 14, "target": 38, "weight": 1.0}, {"source": 13, "target": 42, "weight": 1.3608022562594955}, {"source": 13, "target": 36, "weight": 1.0}, {"source": 13, "target": 40, "weight": 1.0}, {"source": 13, "target": 41, "weight": 1.360602569116716}, {"source": 13, "target": 38, "weight": 1.0}, {"source": 42, "target": 63, "weight": 1.0}, {"source": 42, "target": 72, "weight": 1.0}, {"source": 42, "target": 52, "weight": 1.0}, {"source": 42, "target": 65, "weight": 1.0}, {"source": 42, "target": 50, "weight": 1.0}, {"source": 36, "target": 63, "weight": 1.0}, {"source": 36, "target": 72, "weight": 1.0}, {"source": 36, "target": 52, "weight": 1.0}, {"source": 36, "target": 50, "weight": 1.3603616283082487}, {"source": 40, "target": 63, "weight": 1.0}, {"source": 40, "target": 72, "weight": 1.0}, {"source": 40, "target": 52, "weight": 1.0}, {"source": 40, "target": 65, "weight": 1.360598712467183}, {"source": 40, "target": 50, "weight": 1.0}, {"source": 41, "target": 63, "weight": 1.0}, {"source": 41, "target": 52, "weight": 1.0}, {"source": 41, "target": 65, "weight": 1.360402086152117}, {"source": 41, "target": 50, "weight": 1.0}, {"source": 38, "target": 63, "weight": 1.3601886213046335}, {"source": 38, "target": 72, "weight": 1.0}, {"source": 38, "target": 52, "weight": 1.0}, {"source": 38, "target": 65, "weight": 1.0}, {"source": 63, "target": 93, "weight": 1.3606685405897474}, {"source": 63, "target": 89, "weight": 1.0}, {"source": 63, "target": 79, "weight": 1.0}, {"source": 63, "target": 78, "weight": 1.0}, {"source": 63, "target": 91, "weight": 1.0}, {"source": 72, "target": 93, "weight": 1.0}, {"source": 72, "target": 89, "weight": 1.3624350941949446}, {"source": 72, "target": 79, "weight": 1.0}, {"source": 72, "target": 78, "weight": 1.0}, {"source": 72, "target": 91, "weight": 1.0}, {"source": 52, "target": 93, "weight": 1.0}, {"source": 52, "target": 89, "weight": 1.0}, {"source": 52, "target": 79, "weight": 1.0}, {"source": 52, "target": 78, "weight": 1.0}, {"source": 65, "target": 93, "weight": 1.361451783145555}, {"source": 65, "target": 89, "weight": 1.3606666460846237}, {"source": 65, "target": 79, "weight": 1.0}, {"source": 65, "target": 78, "weight": 1.0}, {"source": 65, "target": 91, "weight": 1.0}, {"source": 50, "target": 93, "weight": 1.0}, {"source": 50, "target": 79, "weight": 1.8697433207458225}, {"source": 50, "target": 91, "weight": 1.0}, {"source": 7, "target": 93, "weight": 1.0}, {"source": 7, "target": 89, "weight": 1.0}, {"source": 7, "target": 78, "weight": 1.0}, {"source": 7, "target": 91, "weight": 1.3605170867820255}, {"source": 21, "target": 93, "weight": 1.0}, {"source": 21, "target": 89, "weight": 1.0}, {"source": 21, "target": 79, "weight": 1.0}, {"source": 21, "target": 78, "weight": 1.0}, {"source": 21, "target": 91, "weight": 1.0}, {"source": 3, "target": 93, "weight": 1.0}, {"source": 3, "target": 89, "weight": 1.0}, {"source": 3, "target": 79, "weight": 1.0}, {"source": 3, "target": 78, "weight": 1.0}, {"source": 3, "target": 91, "weight": 1.0}, {"source": 14, "target": 89, "weight": 1.0}, {"source": 14, "target": 79, "weight": 1.0}, {"source": 14, "target": 78, "weight": 1.0}, {"source": 14, "target": 91, "weight": 1.0}, {"source": 13, "target": 93, "weight": 1.0}, {"source": 13, "target": 89, "weight": 1.0}, {"source": 13, "target": 79, "weight": 1.0}, {"source": 13, "target": 91, "weight": 1.3621330247655863}]}