{"nodes": [{"id": 0, "size": 9, "stability:": 5.297777777777776}, {"id": 1, "size": 1, "stability:": 0.0}, {"id": 2, "size": 56, "stability:": 26.912857142857145}, {"id": 3, "size": 1, "stability:": 0.0}, {"id": 4, "size": 1, "stability:": 0.0}, {"id": 5, "size": 1, "stability:": 0.0}, {"id": 6, "size": 1, "stability:": 0.0}, {"id": 7, "size": 1, "stability:": 0.0}, {"id": 8, "size": 2, "stability:": 0.8099999999999999}, {"id": 9, "size": 2, "stability:": 0.5799999999999998}, {"id": 10, "size": 1, "stability:": 0.0}, {"id": 11, "size": 1, "stability:": 0.0}], "edges": [{"source": 0, "target": 1, "instability": 1.8633333333333333}, {"source": 0, "target": 2, "instability": 9.886438773743768}, {"source": 0, "target": 3, "instability": 1.573333333333333}, {"source": 0, "target": 4, "instability": 1.4433333333333331}, {"source": 0, "target": 5, "instability": 1.3399999999999996}, {"source": 0, "target": 6, "instability": 1.71}, {"source": 0, "target": 7, "instability": 1.19}, {"source": 0, "target": 8, "instability": 1.2138666410369066}, {"source": 0, "target": 9, "instability": 1.8974031961839024}, {"source": 0, "target": 10, "instability": 1.13}, {"source": 0, "target": 11, "instability": 0.7999999999999998}, {"source": 1, "target": 2, "instability": 3.0026800528860873}, {"source": 1, "target": 3, "instability": 0.48}, {"source": 1, "target": 4, "instability": 0.39}, {"source": 1, "target": 5, "instability": 0.4}, {"source": 1, "target": 6, "instability": 0.5}, {"source": 1, "target": 7, "instability": 0.39}, {"source": 1, "target": 8, "instability": 0.3889087296526011}, {"source": 1, "target": 9, "instability": 0.5727564927611034}, {"source": 1, "target": 10, "instability": 0.33}, {"source": 1, "target": 11, "instability": 0.24}, {"source": 2, "target": 3, "instability": 3.7323032433070065}, {"source": 2, "target": 4, "instability": 3.3407655239053047}, {"source": 2, "target": 5, "instability": 3.710922343954013}, {"source": 2, "target": 6, "instability": 4.036981059087171}, {"source": 2, "target": 7, "instability": 3.082858425459815}, {"source": 2, "target": 8, "instability": 3.846733424051411}, {"source": 2, "target": 9, "instability": 4.882356080096693}, {"source": 2, "target": 10, "instability": 3.6240624403324744}, {"source": 2, "target": 11, "instability": 2.620496476951322}, {"source": 3, "target": 4, "instability": 0.56}, {"source": 3, "target": 5, "instability": 0.5}, {"source": 3, "target": 6, "instability": 0.62}, {"source": 3, "target": 7, "instability": 0.44}, {"source": 3, "target": 8, "instability": 0.4737615433949868}, {"source": 3, "target": 9, "instability": 0.6717514421272202}, {"source": 3, "target": 10, "instability": 0.44}, {"source": 3, "target": 11, "instability": 0.31}, {"source": 4, "target": 5, "instability": 0.48}, {"source": 4, "target": 6, "instability": 0.6}, {"source": 4, "target": 7, "instability": 0.41}, {"source": 4, "target": 8, "instability": 0.37476659402887014}, {"source": 4, "target": 9, "instability": 0.6363961030678927}, {"source": 4, "target": 10, "instability": 0.42}, {"source": 4, "target": 11, "instability": 0.31}, {"source": 5, "target": 6, "instability": 0.54}, {"source": 5, "target": 7, "instability": 0.4}, {"source": 5, "target": 8, "instability": 0.5303300858899106}, {"source": 5, "target": 9, "instability": 0.7212489168102785}, {"source": 5, "target": 10, "instability": 0.51}, {"source": 5, "target": 11, "instability": 0.34}, {"source": 6, "target": 7, "instability": 0.49}, {"source": 6, "target": 8, "instability": 0.4666904755831213}, {"source": 6, "target": 9, "instability": 0.7283199846221439}, {"source": 6, "target": 10, "instability": 0.46}, {"source": 6, "target": 11, "instability": 0.35}, {"source": 7, "target": 8, "instability": 0.417193000900063}, {"source": 7, "target": 9, "instability": 0.5868986283848344}, {"source": 7, "target": 10, "instability": 0.38}, {"source": 7, "target": 11, "instability": 0.29}, {"source": 8, "target": 9, "instability": 0.6299999999999999}, {"source": 8, "target": 10, "instability": 0.6576093065034891}, {"source": 8, "target": 11, "instability": 0.5161879502661797}, {"source": 9, "target": 10, "instability": 0.6646803743153546}, {"source": 9, "target": 11, "instability": 0.45254833995939037}, {"source": 10, "target": 11, "instability": 0.71}]}